edgemodelkit/__init__.py
edgemodelkit/edgemodelkit.py
edgemodelkit-2.0.0.dist-info/licenses/LICENSE
edgemodelkit-2.0.0.dist-info/METADATA
edgemodelkit-2.0.0.dist-info/WHEEL
edgemodelkit-2.0.0.dist-info/top_level.txt
edgemodelkit-2.0.0.dist-info/RECORD
