Metadata-Version: 2.4
Name: edgemodelkit
Version: 2.0.0
Summary: edgemodelkit: A Python library for seamless sensor data acquisition and logging.
Home-page: https://github.com/ConsentiumIoT/edgemodelkit
Author: EdgeNeuron
Author-email: official@consentiumiot.com
Project-URL: Bug Tracker, https://github.com/ConsentiumIoT/edgemodelkit/issues
Project-URL: Documentation, https://github.com/ConsentiumIoT/edgemodelkit#readme
Project-URL: Source Code, https://github.com/ConsentiumIoT/edgemodelkit
Keywords: Python,Edge Computing,IoT,Sensor Data,Data Logging,EdgeNeuron,edgemodelkit,Machine Learning
Classifier: Development Status :: 4 - Beta
Classifier: Intended Audience :: Developers
Classifier: Topic :: Software Development :: Libraries :: Application Frameworks
Classifier: License :: OSI Approved :: MIT License
Classifier: Programming Language :: Python :: 3
Classifier: Programming Language :: Python :: 3.7
Classifier: Programming Language :: Python :: 3.8
Classifier: Programming Language :: Python :: 3.9
Classifier: Programming Language :: Python :: 3.10
Classifier: Programming Language :: Python :: 3.11
Classifier: Operating System :: OS Independent
Requires-Python: >=3.7
License-File: LICENSE
Requires-Dist: numpy
Requires-Dist: pandas
Requires-Dist: pyserial
Requires-Dist: tensorflow
Requires-Dist: tqdm
Requires-Dist: joblib
Provides-Extra: dev
Requires-Dist: pytest; extra == "dev"
Requires-Dist: flake8; extra == "dev"
Requires-Dist: black; extra == "dev"
Dynamic: author
Dynamic: author-email
Dynamic: classifier
Dynamic: description
Dynamic: description-content-type
Dynamic: home-page
Dynamic: keywords
Dynamic: license-file
Dynamic: project-url
Dynamic: provides-extra
Dynamic: requires-dist
Dynamic: requires-python
Dynamic: summary
